hw_oa_server/.python-version
hw_oa_server/__init__.py
hw_oa_server/main.py
hw_oa_server/service/__init__.py
hw_oa_server/service/account.py
hw_oa_server/service/http_service.py
hw_oa-0.1.6.dist-info/entry_points.txt
hw_oa-0.1.6.dist-info/METADATA
hw_oa-0.1.6.dist-info/WHEEL
hw_oa-0.1.6.dist-info/RECORD
