Metadata-Version: 2.3
Name: hw-oa
Version: 0.1.6
Summary: 通过提示调用不同api，实现请假、考勤、外出等OA功能
Requires-Python: >=3.10
Classifier: Environment :: MacOS X
Requires-Dist: httpx (>=0.28.1)
Requires-Dist: mcp[cli] (>=1.9.0)
Project-URL: Homepage, https://gitee.com/chenkunlia/hw-oa
